LICENSE
MANIFEST.in
README.md
setup.cfg
setup.py
leetcode/__init__.py
leetcode/__main__.py
leetcode/cli.py
leetcode/terminal.py
leetcode/client/__init__.py
leetcode/client/auth.py
leetcode/client/leetcode.py
leetcode/client/process.py
leetcode/client/quiz.py
leetcode/coding/__init__.py
leetcode/coding/code.py
leetcode/coding/editor.py
leetcode/helper/__init__.py
leetcode/helper/common.py
leetcode/helper/config.py
leetcode/helper/log.py
leetcode/helper/model.py
leetcode/helper/trace.py
leetcode/views/__init__.py
leetcode/views/detail.py
leetcode/views/help.py
leetcode/views/home.py
leetcode/views/loading.py
leetcode/views/result.py
leetcode/views/viewhelper.py
screenshots/Download_on_the_App_Store_Badge_US-UK_135x40.svg
screenshots/list.gif
terminal_leetcode.egg-info/PKG-INFO
terminal_leetcode.egg-info/SOURCES.txt
terminal_leetcode.egg-info/dependency_links.txt
terminal_leetcode.egg-info/entry_points.txt
terminal_leetcode.egg-info/requires.txt
terminal_leetcode.egg-info/top_level.txt