Metadata-Version: 2.1
Name: terminal-leetcode
Version: 0.0.20
Summary: A terminal based leetcode website viewer
Home-page: https://github.com/chishui/terminal-leetcode
Author: Liyun Xiu
Author-email: chishui2@gmail.com
License: MIT
Keywords: leetcode terminal urwid
Platform: UNKNOWN
Classifier: Operating System :: MacOS :: MacOS X
Classifier: Operating System :: POSIX
Classifier: Natural Language :: English
Classifier: Programming Language :: Python :: 3
Classifier: Programming Language :: Python :: 3.7
Classifier: Development Status :: 2 - Pre-Alpha
Classifier: Environment :: Console :: Curses
Classifier: Topic :: Utilities
Classifier: Topic :: Terminals
Classifier: License :: OSI Approved :: MIT License
